cosmoplotlib/__init__.py
cosmoplotlib/layout_engine/__init__.py
cosmoplotlib/layout_engine/_grid.py
cosmoplotlib/pyplot/__init__.py
cosmoplotlib/pyplot/_plots.py
cosmoplotlib-0.1.0.dist-info/LICENSE
cosmoplotlib-0.1.0.dist-info/METADATA
cosmoplotlib-0.1.0.dist-info/WHEEL
cosmoplotlib-0.1.0.dist-info/top_level.txt
cosmoplotlib-0.1.0.dist-info/RECORD
